lama_cleaner/__init__.py
lama_cleaner/benchmark.py
lama_cleaner/const.py
lama_cleaner/helper.py
lama_cleaner/installer.py
lama_cleaner/model_manager.py
lama_cleaner/parse_args.py
lama_cleaner/runtime.py
lama_cleaner/schema.py
lama_cleaner/server.py
lama_cleaner/web_config.py
lama_cleaner/app/build/asset-manifest.json
lama_cleaner/app/build/index.html
lama_cleaner/app/build/static/css/main.6ca672e8.css
lama_cleaner/app/build/static/css/main.bfabee0c.css
lama_cleaner/app/build/static/js/main.587e18e1.js
lama_cleaner/app/build/static/js/main.587e18e1.js.LICENSE.txt
lama_cleaner/app/build/static/js/main.f7f15c17.js
lama_cleaner/app/build/static/js/main.f7f15c17.js.LICENSE.txt
lama_cleaner/app/build/static/media/WorkSans-Black.67c2c5a144333953880b.ttf
lama_cleaner/app/build/static/media/WorkSans-Bold.2bea7a7f7d052c74da25.ttf
lama_cleaner/app/build/static/media/WorkSans-Regular.bb287b894b27372d8ea7.ttf
lama_cleaner/app/build/static/media/WorkSans-SemiBold.1e98db4eb705b586728e.ttf
lama_cleaner/file_manager/__init__.py
lama_cleaner/file_manager/file_manager.py
lama_cleaner/file_manager/storage_backends.py
lama_cleaner/file_manager/utils.py
lama_cleaner/model/__init__.py
lama_cleaner/model/base.py
lama_cleaner/model/controlnet.py
lama_cleaner/model/ddim_sampler.py
lama_cleaner/model/fcf.py
lama_cleaner/model/instruct_pix2pix.py
lama_cleaner/model/lama.py
lama_cleaner/model/ldm.py
lama_cleaner/model/manga.py
lama_cleaner/model/mat.py
lama_cleaner/model/opencv2.py
lama_cleaner/model/paint_by_example.py
lama_cleaner/model/plms_sampler.py
lama_cleaner/model/sd.py
lama_cleaner/model/utils.py
lama_cleaner/model/zits.py
lama_cleaner/model/pipeline/__init__.py
lama_cleaner/model/pipeline/pipeline_stable_diffusion_controlnet_inpaint.py
lama_cleaner/plugins/__init__.py
lama_cleaner/plugins/base_plugin.py
lama_cleaner/plugins/gfpgan_plugin.py
lama_cleaner/plugins/gfpganer.py
lama_cleaner/plugins/gif.py
lama_cleaner/plugins/interactive_seg.py
lama_cleaner/plugins/realesrgan.py
lama_cleaner_custom-0.0.2.dist-info/LICENSE
lama_cleaner_custom-0.0.2.dist-info/METADATA
lama_cleaner_custom-0.0.2.dist-info/WHEEL
lama_cleaner_custom-0.0.2.dist-info/entry_points.txt
lama_cleaner_custom-0.0.2.dist-info/top_level.txt
lama_cleaner_custom-0.0.2.dist-info/RECORD
